tmval/__init__.py
tmval/annuity.py
tmval/bond.py
tmval/constants.py
tmval/conversions.py
tmval/growth.py
tmval/loan.py
tmval/option.py
tmval/portfolio.py
tmval/rate.py
tmval/stock.py
tmval/value.py
tmval-0.0.12.dist-info/LICENSE
tmval-0.0.12.dist-info/METADATA
tmval-0.0.12.dist-info/WHEEL
tmval-0.0.12.dist-info/top_level.txt
tmval-0.0.12.dist-info/RECORD
