Metadata-Version: 2.1
Name: tmval
Version: 0.0.12
Summary: Time Value of Money
Home-page: https://github.com/genedan/TmVal
Author: Gene Dan
Author-email: genedan@gmail.com
License: UNKNOWN
Project-URL: Documentation, https://genedan.com/tmval/docs
Platform: UNKNOWN
Classifier: Programming Language :: Python :: 3.6
Classifier: License :: OSI Approved :: GNU General Public License v3 (GPLv3)
Classifier: Operating System :: POSIX :: Linux
Requires-Python: >=3.6.0
Requires-Dist: numpy
Requires-Dist: python-dateutil
Requires-Dist: scipy
